MBTiles_Segmentation/__init__.py
MBTiles_Segmentation/geometry_wkt_converter.py
MBTiles_Segmentation/mbtiles_handler.py
MBTiles_Segmentation/seg_dataset_creator.py
MBTiles_Segmentation-0.1.1.dist-info/LICENSE
MBTiles_Segmentation-0.1.1.dist-info/METADATA
MBTiles_Segmentation-0.1.1.dist-info/WHEEL
MBTiles_Segmentation-0.1.1.dist-info/entry_points.txt
MBTiles_Segmentation-0.1.1.dist-info/top_level.txt
MBTiles_Segmentation-0.1.1.dist-info/RECORD
