Metadata-Version: 2.1
Name: MBTiles-Segmentation
Version: 0.1.1
Summary: A package for working with MBTiles and generating image-label pairs for semantic segmentation models.
Home-page: https://github.com/masaishi/MBTiles_Segmentation
Author: Masamune Ishihara
Author-email: mwishiha@ucsc.edu
License: MIT License
Requires-Python: >=3.6
License-File: LICENSE
Requires-Dist: pandas
Requires-Dist: mapbox-vector-tile
Requires-Dist: Pillow
